dni/__init__.py
dni/dni.py
dni/dni_network.py
dni/linear_dni.py
dni/linear_sigmoid_dni.py
dni/output_format.py
dni/rnn_dni.py
dni/util.py
pytorch_dni-0.0.1.dist-info/DESCRIPTION.rst
pytorch_dni-0.0.1.dist-info/METADATA
pytorch_dni-0.0.1.dist-info/RECORD
pytorch_dni-0.0.1.dist-info/WHEEL
pytorch_dni-0.0.1.dist-info/metadata.json
pytorch_dni-0.0.1.dist-info/top_level.txt
